{
  "module_platform_id": "platform:f35",
  "distribution": {
    "name": "fedora-35",
    "description": "Fedora Linux 35",
    "no_package_list": true,
    "restricted_access": true
  },
  "x86_64": {
    "image_types": [
      "aws",
      "azure",
      "guest-image",
      "vsphere",
      "edge-commit"
    ],
    "repositories": [
      {
        "id": "fedora",
        "metalink": "https://mirrors.fedoraproject.org/metalink?repo=fedora-35&arch=x86_64",
        "rhsm": false
      },
      {
        "id": "updates",
        "metalink": "https://mirrors.fedoraproject.org/metalink?repo=updates-released-f35&arch=x86_64",
        "rhsm": false
      },
      {
        "name": "fedora-modular",
        "metalink": "https://mirrors.fedoraproject.org/metalink?repo=fedora-modular-35&arch=x86_64",
        "rhsm": false
      },
      {
        "name": "updates-modular",
        "metalink": "https://mirrors.fedoraproject.org/metalink?repo=updates-released-modular-f35&arch=x86_64",
        "rhsm": false
      }
    ]
  }
}
