[
  {
    "name": "centos-release-advanced-virtualization",
    "summary": "Advanced Virtualization packages from the CentOS Virtualization SIG repository"
  },
  {
    "name": "centos-release-ansible-29",
    "summary": "Ansible 2.9 packages from the CentOS ConfigManagement SIG repository"
  },
  {
    "name": "centos-release-ceph-nautilus",
    "summary": "Ceph Nautilus packages from the CentOS Storage SIG repository"
  },
  {
    "name": "centos-release-ceph-octopus",
    "summary": "Ceph Octopus packages from the CentOS Storage SIG repository"
  },
  {
    "name": "centos-release-ceph-pacific",
    "summary": "Ceph Pacific packages from the CentOS Storage SIG repository"
  },
  {
    "name": "centos-release-ceph-quincy",
    "summary": "Ceph Quincy packages from the CentOS Storage SIG repository"
  },
  {
    "name": "centos-release-configmanagement",
    "summary": "Release file for ConfigManagement SIG repository"
  },
  {
    "name": "centos-release-gluster10",
    "summary": "Gluster 10 packages from the CentOS Storage SIG repository"
  },
  {
    "name": "centos-release-gluster6",
    "summary": "Gluster 6 packages from the CentOS Storage SIG repository"
  },
  {
    "name": "centos-release-gluster7",
    "summary": "Gluster 7 packages from the CentOS Storage SIG repository"
  },
  {
    "name": "centos-release-gluster8",
    "summary": "Gluster 8 packages from the CentOS Storage SIG repository"
  },
  {
    "name": "centos-release-gluster9",
    "summary": "Gluster 9 packages from the CentOS Storage SIG repository"
  },
  {
    "name": "centos-release-hyperscale",
    "summary": "CentOS Hyperscale SIG main repo configs"
  },
  {
    "name": "centos-release-hyperscale-experimental",
    "summary": "CentOS Hyperscale SIG experimental repo configs"
  },
  {
    "name": "centos-release-hyperscale-hotfixes",
    "summary": "CentOS Hyperscale SIG module hotfixes repo configs"
  },
  {
    "name": "centos-release-hyperscale-spin",
    "summary": "CentOS Hyperscale SIG spin repo configs"
  },
  {
    "name": "centos-release-kmods",
    "summary": "CentOS Kmods SIG repository configs"
  },
  {
    "name": "centos-release-kmods-rebuild",
    "summary": "CentOS Kmods SIG rebuild repo configs"
  },
  {
    "name": "centos-release-messaging",
    "summary": "Config to enable the repository for the Messaging SIG"
  },
  {
    "name": "centos-release-nfs-ganesha28",
    "summary": "NFS-Ganesha 2.8 packages from the CentOS Storage SIG repository"
  },
  {
    "name": "centos-release-nfs-ganesha30",
    "summary": "NFS-Ganesha 3 packages from the CentOS Storage SIG repository"
  },
  {
    "name": "centos-release-nfs-ganesha4",
    "summary": "NFS-Ganesha 4 packages from the CentOS Storage SIG repository"
  },
  {
    "name": "centos-release-nfv-common",
    "summary": "Common package to contain NFV SIG"
  },
  {
    "name": "centos-release-nfv-extras",
    "summary": "Release file to establish repo config for NFV network extras repo"
  },
  {
    "name": "centos-release-nfv-openvswitch",
    "summary": "Common release file to establish shared metadata for CentOS NFV SIG"
  },
  {
    "name": "centos-release-openstack-train",
    "summary": "OpenStack from the CentOS Cloud SIG repo configs"
  },
  {
    "name": "centos-release-openstack-ussuri",
    "summary": "OpenStack from the CentOS Cloud SIG repo configs"
  },
  {
    "name": "centos-release-openstack-victoria",
    "summary": "OpenStack from the CentOS Cloud SIG repo configs"
  },
  {
    "name": "centos-release-openstack-wallaby",
    "summary": "OpenStack from the CentOS Cloud SIG repo configs"
  },
  {
    "name": "centos-release-openstack-xena",
    "summary": "OpenStack from the CentOS Cloud SIG repo configs"
  },
  {
    "name": "centos-release-opstools",
    "summary": "Config to enable the repository for OpsTools SIG"
  },
  {
    "name": "centos-release-ovirt44",
    "summary": "oVirt 4.4 packages from the CentOS Virtualization SIG repository"
  },
  {
    "name": "centos-release-ovirt45",
    "summary": "oVirt 4.5 packages from the CentOS Virtualization SIG repository"
  },
  {
    "name": "centos-release-plus",
    "summary": "CentOS Plus repository"
  },
  {
    "name": "centos-release-qpid-proton",
    "summary": "Config to enable the Messaging SIG QPID Proton packages"
  },
  {
    "name": "centos-release-rabbitmq-38",
    "summary": "Config to enable the repository for the Messaging SIG RabbitMQ Server"
  },
  {
    "name": "centos-release-samba411",
    "summary": "Samba 4.11 packages from the CentOS Storage SIG repository"
  },
  {
    "name": "centos-release-samba412",
    "summary": "Samba 4.12 packages from the CentOS Storage SIG repository"
  },
  {
    "name": "centos-release-samba413",
    "summary": "Samba 4.13 packages from the CentOS Storage SIG repository"
  },
  {
    "name": "centos-release-samba414",
    "summary": "Samba 4.14 packages from the CentOS Storage SIG repository"
  },
  {
    "name": "centos-release-samba415",
    "summary": "Samba 4.15 packages from the CentOS Storage SIG repository"
  },
  {
    "name": "centos-release-samba416",
    "summary": "Samba 4.16 packages from the CentOS Storage SIG repository"
  },
  {
    "name": "centos-release-storage-common",
    "summary": "Common release file to establish shared metadata for CentOS Storage SIG"
  },
  {
    "name": "centos-release-stream",
    "summary": "CentOS-Stream release file"
  },
  {
    "name": "centos-release-virt-common",
    "summary": "Common release file to establish shared metadata for CentOS Virt SIG"
  },
  {
    "name": "cpaste",
    "summary": "Command line tool to upload things to pastebin.centos.org"
  },
  {
    "name": "elrepo-release",
    "summary": "ELRepo.org Community Enterprise Linux Repository release file"
  },
  {
    "name": "epel-next-release",
    "summary": "Extra Packages for Enterprise Linux Next repository configuration"
  },
  {
    "name": "epel-release",
    "summary": "Extra Packages for Enterprise Linux repository configuration"
  }
]
